_verzeichnisdienst_version.py
verzeichnisdienst/__init__.py
verzeichnisdienst/py.typed
verzeichnisdienst/v1/__init__.py
verzeichnisdienst/v1/_autogenerated.py
verzeichnisdienst/v1/_autogenerated_websocket.py
verzeichnisdienst/v1/models.py
verzeichnisdienst/v1/websocket.py
verzeichnisdienst-0.1.0.dist-info/METADATA
verzeichnisdienst-0.1.0.dist-info/WHEEL
verzeichnisdienst-0.1.0.dist-info/RECORD
