Metadata-Version: 2.3
Name: verzeichnisdienst
Version: 0.1.0
Summary: Model classes for the Verzeichnisdienst API by EDI@Energy
Project-URL: Changelog, https://github.com/Hochfrequenz/verzeichnisdienst-python-models/releases
Project-URL: Homepage, https://github.com/Hochfrequenz/verzeichnisdienst-python-models
Author-email: your name <info+github@hochfrequenz.de>
License: MIT
Keywords: BDEW,EDI@Energy,Verzeichnisdienst
Classifier: Development Status :: 4 - Beta
Classifier: Environment :: Console
Classifier: Intended Audience :: Developers
Classifier: License :: OSI Approved :: MIT License
Classifier: Operating System :: OS Independent
Classifier: Programming Language :: Python
Classifier: Programming Language :: Python :: 3 :: Only
Classifier: Programming Language :: Python :: 3.9
Classifier: Programming Language :: Python :: 3.10
Classifier: Programming Language :: Python :: 3.11
Classifier: Programming Language :: Python :: 3.12
Classifier: Programming Language :: Python :: 3.13
Requires-Python: >=3.9
Requires-Dist: pydantic>=2
Provides-Extra: codegen
Requires-Dist: datamodel-code-generator==0.26.3; extra == 'codegen'
Provides-Extra: coverage
Requires-Dist: coverage==7.6.7; extra == 'coverage'
Provides-Extra: dev
Requires-Dist: pip-tools; extra == 'dev'
Provides-Extra: formatting
Requires-Dist: black==24.10.0; extra == 'formatting'
Requires-Dist: isort==5.13.2; extra == 'formatting'
Provides-Extra: linting
Requires-Dist: pylint==3.3.1; extra == 'linting'
Provides-Extra: packaging
Requires-Dist: build==1.2.2.post1; extra == 'packaging'
Requires-Dist: twine==5.1.1; extra == 'packaging'
Provides-Extra: spell-check
Requires-Dist: codespell==2.3.0; extra == 'spell-check'
Provides-Extra: tests
Requires-Dist: pytest==8.3.3; extra == 'tests'
Provides-Extra: type-check
Requires-Dist: mypy[pydantic]==1.13.0; extra == 'type-check'
